alexandra_ai/__init__.py
alexandra_ai-0.1.0.dist-info/LICENSE
alexandra_ai-0.1.0.dist-info/WHEEL
alexandra_ai-0.1.0.dist-info/METADATA
alexandra_ai-0.1.0.dist-info/RECORD
