Metadata-Version: 2.1
Name: alexandra-ai
Version: 0.1.0
Summary: Alexandra Institute Artificial Intelligence, a Python package for Danish data science.
License: MIT
Author: Dan Saattrup Nielsen
Author-email: dan.nielsen@alexandra.dk
Requires-Python: >=3.8,<3.11
Classifier: License :: OSI Approved :: MIT License
Classifier: Programming Language :: Python :: 3
Classifier: Programming Language :: Python :: 3.8
Classifier: Programming Language :: Python :: 3.9
Classifier: Programming Language :: Python :: 3.10
Requires-Dist: alexandra-ai-eval (>=0.1.0,<0.2.0)
